pantsbuild.pants.contrib.confluence-1.30.4-py3.6-nspkg.pth
pants/contrib/confluence/__init__.py
pants/contrib/confluence/register.py
pants/contrib/confluence/tasks/__init__.py
pants/contrib/confluence/tasks/confluence_publish.py
pants/contrib/confluence/util/__init__.py
pants/contrib/confluence/util/confluence_util.py
pantsbuild.pants.contrib.confluence-1.30.4.dist-info/METADATA
pantsbuild.pants.contrib.confluence-1.30.4.dist-info/RECORD
pantsbuild.pants.contrib.confluence-1.30.4.dist-info/WHEEL
pantsbuild.pants.contrib.confluence-1.30.4.dist-info/entry_points.txt
pantsbuild.pants.contrib.confluence-1.30.4.dist-info/namespace_packages.txt
pantsbuild.pants.contrib.confluence-1.30.4.dist-info/top_level.txt
pantsbuild.pants.contrib.confluence-1.30.4.dist-info/zip-safe
